CHANGELOG.txt
LISCENCE.txt
MANIFEST.in
README.txt
setup.py
beta/client.py
beta/module.py
beta/server.py
beta/temp.py
beta/.venv/Lib/site-packages/_distutils_hack/__init__.py
beta/.venv/Lib/site-packages/_distutils_hack/override.py
beta/.venv/Lib/site-packages/pip/__init__.py
beta/.venv/Lib/site-packages/pip/__main__.py
beta/.venv/Lib/site-packages/pip/__pip-runner__.py
beta/.venv/Lib/site-packages/pip-24.0.dist-info/AUTHORS.txt
beta/.venv/Lib/site-packages/pip-24.0.dist-info/LICENSE.txt
beta/.venv/Lib/site-packages/pip-24.0.dist-info/entry_points.txt
beta/.venv/Lib/site-packages/pip-24.0.dist-info/top_level.txt
beta/.venv/Lib/site-packages/pip/_internal/__init__.py
beta/.venv/Lib/site-packages/pip/_internal/build_env.py
beta/.venv/Lib/site-packages/pip/_internal/cache.py
beta/.venv/Lib/site-packages/pip/_internal/configuration.py
beta/.venv/Lib/site-packages/pip/_internal/exceptions.py
beta/.venv/Lib/site-packages/pip/_internal/main.py
beta/.venv/Lib/site-packages/pip/_internal/pyproject.py
beta/.venv/Lib/site-packages/pip/_internal/self_outdated_check.py
beta/.venv/Lib/site-packages/pip/_internal/wheel_builder.py
beta/.venv/Lib/site-packages/pip/_internal/cli/__init__.py
beta/.venv/Lib/site-packages/pip/_internal/cli/autocompletion.py
beta/.venv/Lib/site-packages/pip/_internal/cli/base_command.py
beta/.venv/Lib/site-packages/pip/_internal/cli/cmdoptions.py
beta/.venv/Lib/site-packages/pip/_internal/cli/command_context.py
beta/.venv/Lib/site-packages/pip/_internal/cli/main.py
beta/.venv/Lib/site-packages/pip/_internal/cli/main_parser.py
beta/.venv/Lib/site-packages/pip/_internal/cli/parser.py
beta/.venv/Lib/site-packages/pip/_internal/cli/progress_bars.py
beta/.venv/Lib/site-packages/pip/_internal/cli/req_command.py
beta/.venv/Lib/site-packages/pip/_internal/cli/spinners.py
beta/.venv/Lib/site-packages/pip/_internal/cli/status_codes.py
beta/.venv/Lib/site-packages/pip/_internal/commands/__init__.py
beta/.venv/Lib/site-packages/pip/_internal/commands/cache.py
beta/.venv/Lib/site-packages/pip/_internal/commands/check.py
beta/.venv/Lib/site-packages/pip/_internal/commands/completion.py
beta/.venv/Lib/site-packages/pip/_internal/commands/configuration.py
beta/.venv/Lib/site-packages/setuptools-65.5.0.dist-info/entry_points.txt
beta/.venv/Lib/site-packages/setuptools-65.5.0.dist-info/top_level.txt
easy_socket.egg-info/SOURCES.txt
easy_socket.egg-info/dependency_links.txt
easy_socket.egg-info/top_level.txt
super_easy_socket.egg-info/PKG-INFO
super_easy_socket.egg-info/SOURCES.txt
super_easy_socket.egg-info/dependency_links.txt
super_easy_socket.egg-info/top_level.txt