Metadata-Version: 2.1
Name: super-easy-socket
Version: 0.0.2
Summary: A Python module designed to simplify the implementation of socket-based server-client communication
Home-page: 
Author: Theodor Billek
Author-email: HilbertLooked@gmail.com
License: MIT
Keywords: super-easy-socket
Classifier: Development Status :: 5 - Production/Stable
Classifier: Intended Audience :: Education
Classifier: Operating System :: Microsoft :: Windows :: Windows 10
Classifier: License :: OSI Approved :: MIT License
Classifier: Programming Language :: Python :: 3
